<?xml version="1.0" encoding="utf-8"?>
<SoundBanksInfo Platform="Windows" BasePlatform="Windows" SchemaVersion="10" SoundbankVersion="113">
	<RootPaths>
		<ProjectRoot>C:\projects\civ6\Civ6\Wwise\Civ6 Project\</ProjectRoot>
		<SourceFilesRoot>C:\projects\civ6\Civ6\Wwise\Civ6 Project\.cache\Windows\</SourceFilesRoot>
		<SoundBanksRoot>C:\projects\civ6\Civ6\Wwise\Civ6 Project\GeneratedSoundBanks\Windows\</SoundBanksRoot>
		<ExternalSourcesInputFile></ExternalSourcesInputFile>
		<ExternalSourcesOutputRoot>C:\projects\civ6\Civ6\Wwise\Civ6 Project\GeneratedSoundBanks\Windows</ExternalSourcesOutputRoot>
	</RootPaths>
	<SoundBanks>
		<SoundBank Id="2086146056" GUID="{7A26C53E-9A3C-4CEB-984C-73A61B413E26}" Language="SFX">
			<ShortName>DLC05_Unit_Bank_2D</ShortName>
			<Path>DLC05_Unit_Bank_2D.bnk</Path>
			<IncludedEvents>
				<Event Id="804187966" Name="High_Priestess_Build_2D" GUID="{EA804473-4FEA-442A-9490-B35988120A64}"/>
				<Event Id="3735904875" Name="Stop_Unit_Move_2D_High_Priestess" GUID="{2C7A1F7C-C7B7-442C-8CB1-2D2B97D2C193}"/>
				<Event Id="2341715744" Name="Stop_Unit_Move_2D_Medjay" GUID="{ED34FAC2-AC28-4527-B224-A70DF2117DE4}"/>
				<Event Id="1193239339" Name="Unit_Attack_2D_High_Priestess" GUID="{24035660-7947-4033-BA18-C5ECC430BA30}"/>
				<Event Id="1129110240" Name="Unit_Attack_2D_Medjay" GUID="{F140CF34-B47A-4CE5-B67B-D50DB5C13B3B}"/>
				<Event Id="4132343371" Name="Unit_Combat_Lose_2D_High_Priestess" GUID="{85FC002B-7C5A-4A37-8F01-A1535A87AD32}"/>
				<Event Id="1000391616" Name="Unit_Combat_Lose_2D_Medjay" GUID="{0F719AF0-89F3-4E72-946F-10B6A58E2DD8}"/>
				<Event Id="815910413" Name="Unit_Death_2D_High_Priestess" GUID="{DBC44516-D081-4181-9F4C-D858D14438A8}"/>
				<Event Id="2667440606" Name="Unit_Death_2D_Medjay" GUID="{F92B5874-282A-4268-90D3-EC047420522C}"/>
				<Event Id="3658493155" Name="Unit_Disembark_2D_High_Priestess" GUID="{088B4277-8289-4690-BEE5-43CF26195484}"/>
				<Event Id="4230110904" Name="Unit_Disembark_2D_Medjay" GUID="{11E739CD-34A1-4338-9141-0A3DB248E9E7}"/>
				<Event Id="1178545255" Name="Unit_Embark_2D_High_Priestess" GUID="{41326C4F-ABB9-4623-8E22-510BBB0566DE}"/>
				<Event Id="1902670812" Name="Unit_Embark_2D_Medjay" GUID="{F4ADAA25-C995-4177-B128-87F1C78AA196}"/>
				<Event Id="406943672" Name="Unit_Move_2D_High_Priestess" GUID="{6F1BBF14-A123-4A41-BFF9-DBC80546BC2F}"/>
				<Event Id="1872572579" Name="Unit_Move_2D_Medjay" GUID="{AE346BAC-BCD3-47F1-AFFF-FD5FF2331EE2}"/>
				<Event Id="3449463557" Name="Unit_Selected_High_Priestess" GUID="{F27F817C-1B97-4819-9A0C-A3F5A839E9A8}"/>
				<Event Id="50346582" Name="Unit_Selected_Medjay" GUID="{86F78FFB-817D-4D42-AF06-65643F2C62F8}"/>
			</IncludedEvents>
			<ReferencedStreamedFiles>
				<File Id="68069817" Language="SFX">
					<ShortName>SelectUnitBase-000.wav</ShortName>
					<Path>SFX\SelectUnitBase-000_10F921B3_BF4BB6EC.wem</Path>
				</File>
				<File Id="136132561" Language="SFX">
					<ShortName>SelectApostle_1.wav</ShortName>
					<Path>SFX\SelectApostle_1_E1E65BF4.wem</Path>
				</File>
				<File Id="219679802" Language="SFX">
					<ShortName>BattleScape02.wav</ShortName>
					<Path>SFX\BattleScape02_867CB3AC.wem</Path>
				</File>
				<File Id="232943153" Language="SFX">
					<ShortName>SelectUnitBase-001.wav</ShortName>
					<Path>SFX\SelectUnitBase-001_10F921B3_BF4BB6EC.wem</Path>
				</File>
				<File Id="251474999" Language="SFX">
					<ShortName>BattleScape01.wav</ShortName>
					<Path>SFX\BattleScape01_E458780A.wem</Path>
				</File>
				<File Id="256404603" Language="SFX">
					<ShortName>SelectMissionary_1.wav</ShortName>
					<Path>SFX\SelectMissionary_1_E1E65BF4.wem</Path>
				</File>
				<File Id="395413359" Language="SFX">
					<ShortName>ClubSwing-003.wav</ShortName>
					<Path>SFX\ClubSwing-003_10F921B3.wem</Path>
				</File>
				<File Id="442456153" Language="SFX">
					<ShortName>BattleScape03.wav</ShortName>
					<Path>SFX\BattleScape03_EA8A4EFB.wem</Path>
				</File>
				<File Id="546845240" Language="SFX">
					<ShortName>ClubSwing-005.wav</ShortName>
					<Path>SFX\ClubSwing-005_10F921B3.wem</Path>
				</File>
				<File Id="551845694" Language="SFX">
					<ShortName>ClubSwing-001.wav</ShortName>
					<Path>SFX\ClubSwing-001_10F921B3.wem</Path>
				</File>
				<File Id="733402780" Language="SFX">
					<ShortName>ClubSwing-002.wav</ShortName>
					<Path>SFX\ClubSwing-002_10F921B3.wem</Path>
				</File>
				<File Id="750742473" Language="SFX">
					<ShortName>BattleScape04.wav</ShortName>
					<Path>SFX\BattleScape04_FAE949F2.wem</Path>
				</File>
				<File Id="803199237" Language="SFX">
					<ShortName>Apostle_Death_Effect_1.wav</ShortName>
					<Path>SFX\Apostle_Death_Effect_1_DDC6F2B5.wem</Path>
				</File>
				<File Id="809304804" Language="SFX">
					<ShortName>ClubSwing-000.wav</ShortName>
					<Path>SFX\ClubSwing-000_10F921B3.wem</Path>
				</File>
				<File Id="836252571" Language="SFX">
					<ShortName>ClubSwing-004.wav</ShortName>
					<Path>SFX\ClubSwing-004_10F921B3.wem</Path>
				</File>
				<File Id="1055338685" Language="SFX">
					<ShortName>Apostle_Death_Effect.wav</ShortName>
					<Path>SFX\Apostle_Death_Effect_E1E65BF4.wem</Path>
				</File>
			</ReferencedStreamedFiles>
			<IncludedMemoryFiles>
				<File Id="359040" Language="SFX">
					<ShortName>ShipRopeCreak_1.wav</ShortName>
					<Path>SFX\ShipRopeCreak_1_10F921B3.wem</Path>
				</File>
				<File Id="807448" Language="SFX">
					<ShortName>ShipWoodCreakLow_0.wav</ShortName>
					<Path>SFX\ShipWoodCreakLow_0_10F921B3.wem</Path>
				</File>
				<File Id="2155001" Language="SFX">
					<ShortName>ShipRunSplash_0.wav</ShortName>
					<Path>SFX\ShipRunSplash_0_10F921B3.wem</Path>
				</File>
				<File Id="2289841" Language="SFX">
					<ShortName>ShipWoodCreak_6.wav</ShortName>
					<Path>SFX\ShipWoodCreak_6_10F921B3.wem</Path>
				</File>
				<File Id="2676839" Language="SFX">
					<ShortName>FootSand-004.wav</ShortName>
					<Path>SFX\FootSand-004_10F921B3.wem</Path>
				</File>
				<File Id="2966701" Language="SFX">
					<ShortName>ShipSailFlap_12.wav</ShortName>
					<Path>SFX\ShipSailFlap_12_10F921B3.wem</Path>
				</File>
				<File Id="3568867" Language="SFX">
					<ShortName>FootstepDirt05.wav</ShortName>
					<Path>SFX\FootstepDirt05_10F921B3.wem</Path>
				</File>
				<File Id="4140251" Language="SFX">
					<ShortName>FootstepDirt00.wav</ShortName>
					<Path>SFX\FootstepDirt00_10F921B3.wem</Path>
				</File>
				<File Id="4238673" Language="SFX">
					<ShortName>ShipSailFlap_2.wav</ShortName>
					<Path>SFX\ShipSailFlap_2_10F921B3.wem</Path>
				</File>
				<File Id="4563338" Language="SFX">
					<ShortName>Vox_E_Death_04.wav</ShortName>
					<Path>SFX\Vox_E_Death_04_10F921B3.wem</Path>
				</File>
				<File Id="4708022" Language="SFX">
					<ShortName>ShipSailFlap_3.wav</ShortName>
					<Path>SFX\ShipSailFlap_3_10F921B3.wem</Path>
				</File>
				<File Id="5016774" Language="SFX">
					<ShortName>ShipWoodCreak_5.wav</ShortName>
					<Path>SFX\ShipWoodCreak_5_10F921B3.wem</Path>
				</File>
				<File Id="5116324" Language="SFX">
					<ShortName>FootstepGrass03.wav</ShortName>
					<Path>SFX\FootstepGrass03_10F921B3.wem</Path>
				</File>
				<File Id="5324596" Language="SFX">
					<ShortName>ShipRopeCreak_5.wav</ShortName>
					<Path>SFX\ShipRopeCreak_5_10F921B3.wem</Path>
				</File>
				<File Id="5895148" Language="SFX">
					<ShortName>ShipRunSplash_1.wav</ShortName>
					<Path>SFX\ShipRunSplash_1_10F921B3.wem</Path>
				</File>
				<File Id="5974517" Language="SFX">
					<ShortName>ShipWoodCreakLow_1.wav</ShortName>
					<Path>SFX\ShipWoodCreakLow_1_10F921B3.wem</Path>
				</File>
				<File Id="6999894" Language="SFX">
					<ShortName>ShipRunStop_0.wav</ShortName>
					<Path>SFX\ShipRunStop_0_10F921B3.wem</Path>
				</File>
				<File Id="7139734" Language="SFX">
					<ShortName>ShipWoodCreak_2.wav</ShortName>
					<Path>SFX\ShipWoodCreak_2_10F921B3.wem</Path>
				</File>
				<File Id="7235225" Language="SFX">
					<ShortName>FootstepLeaves-003.wav</ShortName>
					<Path>SFX\FootstepLeaves-003_10F921B3.wem</Path>
				</File>
				<File Id="7339847" Language="SFX">
					<ShortName>ShipWoodCreak_4.wav</ShortName>
					<Path>SFX\ShipWoodCreak_4_10F921B3.wem</Path>
				</File>
				<File Id="7913810" Language="SFX">
					<ShortName>ShipRopeCreak_3.wav</ShortName>
					<Path>SFX\ShipRopeCreak_3_10F921B3.wem</Path>
				</File>
				<File Id="8145725" Language="SFX">
					<ShortName>FootstepMud02.wav</ShortName>
					<Path>SFX\FootstepMud02_10F921B3.wem</Path>
				</File>
				<File Id="8554450" Language="SFX">
					<ShortName>FootstepMud00.wav</ShortName>
					<Path>SFX\FootstepMud00_10F921B3.wem</Path>
				</File>
				<File Id="9520795" Language="SFX">
					<ShortName>FootSand-001.wav</ShortName>
					<Path>SFX\FootSand-001_10F921B3.wem</Path>
				</File>
				<File Id="9744443" Language="SFX">
					<ShortName>ShipWoodCreak_9.wav</ShortName>
					<Path>SFX\ShipWoodCreak_9_10F921B3.wem</Path>
				</File>
				<File Id="9942262" Language="SFX">
					<ShortName>ImpactBluntFlesh-004.wav</ShortName>
					<Path>SFX\ImpactBluntFlesh-004_10F921B3.wem</Path>
				</File>
				<File Id="10211388" Language="SFX">
					<ShortName>FootSnow-003.wav</ShortName>
					<Path>SFX\FootSnow-003_10F921B3.wem</Path>
				</File>
				<File Id="10694798" Language="SFX">
					<ShortName>ShipSailFlap_8.wav</ShortName>
					<Path>SFX\ShipSailFlap_8_10F921B3.wem</Path>
				</File>
				<File Id="10786571" Language="SFX">
					<ShortName>FootstepLeaves-002.wav</ShortName>
					<Path>SFX\FootstepLeaves-002_10F921B3.wem</Path>
				</File>
				<File Id="11636066" Language="SFX">
					<ShortName>ShipWoodCreak_7.wav</ShortName>
					<Path>SFX\ShipWoodCreak_7_10F921B3.wem</Path>
				</File>
				<File Id="12901590" Language="SFX">
					<ShortName>FootstepLeaves-006.wav</ShortName>
					<Path>SFX\FootstepLeaves-006_10F921B3.wem</Path>
				</File>
				<File Id="16248382" Language="SFX">
					<ShortName>FootstepLeaves-001.wav</ShortName>
					<Path>SFX\FootstepLeaves-001_10F921B3.wem</Path>
				</File>
				<File Id="16473378" Language="SFX">
					<ShortName>ShipSailFlap_11.wav</ShortName>
					<Path>SFX\ShipSailFlap_11_10F921B3.wem</Path>
				</File>
				<File Id="17539624" Language="SFX">
					<ShortName>FootstepLeaves-000.wav</ShortName>
					<Path>SFX\FootstepLeaves-000_10F921B3.wem</Path>
				</File>
				<File Id="17823896" Language="SFX">
					<ShortName>ShipSailFlap_10.wav</ShortName>
					<Path>SFX\ShipSailFlap_10_10F921B3.wem</Path>
				</File>
				<File Id="18876312" Language="SFX">
					<ShortName>ShipRopeCreak_2.wav</ShortName>
					<Path>SFX\ShipRopeCreak_2_10F921B3.wem</Path>
				</File>
				<File Id="21080884" Language="SFX">
					<ShortName>FootstepMud03.wav</ShortName>
					<Path>SFX\FootstepMud03_10F921B3.wem</Path>
				</File>
				<File Id="21236719" Language="SFX">
					<ShortName>ShipSailFlap_6.wav</ShortName>
					<Path>SFX\ShipSailFlap_6_10F921B3.wem</Path>
				</File>
				<File Id="21781332" Language="SFX">
					<ShortName>ShipRopeCreak_6.wav</ShortName>
					<Path>SFX\ShipRopeCreak_6_10F921B3.wem</Path>
				</File>
				<File Id="21853954" Language="SFX">
					<ShortName>ShipRopeCreak_7.wav</ShortName>
					<Path>SFX\ShipRopeCreak_7_10F921B3.wem</Path>
				</File>
				<File Id="22852928" Language="SFX">
					<ShortName>ShipRunStop_2.wav</ShortName>
					<Path>SFX\ShipRunStop_2_10F921B3.wem</Path>
				</File>
				<File Id="23029459" Language="SFX">
					<ShortName>ShipSailFlap_7.wav</ShortName>
					<Path>SFX\ShipSailFlap_7_10F921B3.wem</Path>
				</File>
				<File Id="23569963" Language="SFX">
					<ShortName>ImpactBluntFlesh-002.wav</ShortName>
					<Path>SFX\ImpactBluntFlesh-002_10F921B3.wem</Path>
				</File>
				<File Id="27464110" Language="SFX">
					<ShortName>ShipSailFlap_4.wav</ShortName>
					<Path>SFX\ShipSailFlap_4_10F921B3.wem</Path>
				</File>
				<File Id="28879047" Language="SFX">
					<ShortName>FootstepLeaves-008.wav</ShortName>
					<Path>SFX\FootstepLeaves-008_10F921B3.wem</Path>
				</File>
				<File Id="30153914" Language="SFX">
					<ShortName>ImpactBluntFlesh-000.wav</ShortName>
					<Path>SFX\ImpactBluntFlesh-000_10F921B3.wem</Path>
				</File>
				<File Id="31929011" Language="SFX">
					<ShortName>ShipWoodCreak_1.wav</ShortName>
					<Path>SFX\ShipWoodCreak_1_10F921B3.wem</Path>
				</File>
				<File Id="32700301" Language="SFX">
					<ShortName>ShipRopeCreak_4.wav</ShortName>
					<Path>SFX\ShipRopeCreak_4_10F921B3.wem</Path>
				</File>
				<File Id="32754051" Language="SFX">
					<ShortName>FootstepLeaves-007.wav</ShortName>
					<Path>SFX\FootstepLeaves-007_10F921B3.wem</Path>
				</File>
				<File Id="33743282" Language="SFX">
					<ShortName>Vox_E_Death_01.wav</ShortName>
					<Path>SFX\Vox_E_Death_01_10F921B3.wem</Path>
				</File>
				<File Id="35162153" Language="SFX">
					<ShortName>ShipWoodCreak_3.wav</ShortName>
					<Path>SFX\ShipWoodCreak_3_10F921B3.wem</Path>
				</File>
				<File Id="35249602" Language="SFX">
					<ShortName>FootSand-005.wav</ShortName>
					<Path>SFX\FootSand-005_10F921B3.wem</Path>
				</File>
				<File Id="37248400" Language="SFX">
					<ShortName>CaravelRunStart_0.wav</ShortName>
					<Path>SFX\CaravelRunStart_0_10F921B3.wem</Path>
				</File>
				<File Id="37387630" Language="SFX">
					<ShortName>FootRiverCoast-003.wav</ShortName>
					<Path>SFX\FootRiverCoast-003_10F921B3.wem</Path>
				</File>
				<File Id="39768352" Language="SFX">
					<ShortName>FootRiverCoast-002.wav</ShortName>
					<Path>SFX\FootRiverCoast-002_10F921B3.wem</Path>
				</File>
				<File Id="40980442" Language="SFX">
					<ShortName>ShipSailFlap_1.wav</ShortName>
					<Path>SFX\ShipSailFlap_1_10F921B3.wem</Path>
				</File>
				<File Id="42538167" Language="SFX">
					<ShortName>ShipWoodCreak_0.wav</ShortName>
					<Path>SFX\ShipWoodCreak_0_10F921B3.wem</Path>
				</File>
				<File Id="42884239" Language="SFX">
					<ShortName>BoneBreaks-004.wav</ShortName>
					<Path>SFX\BoneBreaks-004_D1886220.wem</Path>
				</File>
				<File Id="43422929" Language="SFX">
					<ShortName>FoleyClothShort-006.wav</ShortName>
					<Path>SFX\FoleyClothShort-006_10F921B3.wem</Path>
				</File>
				<File Id="46066412" Language="SFX">
					<ShortName>ShipWoodCreak_8.wav</ShortName>
					<Path>SFX\ShipWoodCreak_8_10F921B3.wem</Path>
				</File>
				<File Id="46619817" Language="SFX">
					<ShortName>FootRiverCoast-006.wav</ShortName>
					<Path>SFX\FootRiverCoast-006_10F921B3.wem</Path>
				</File>
				<File Id="47262210" Language="SFX">
					<ShortName>FoleyBagsAncient0.wav</ShortName>
					<Path>SFX\FoleyBagsAncient0_10F921B3.wem</Path>
				</File>
				<File Id="49973669" Language="SFX">
					<ShortName>FootSnow-004.wav</ShortName>
					<Path>SFX\FootSnow-004_10F921B3.wem</Path>
				</File>
				<File Id="50279685" Language="SFX">
					<ShortName>FootstepGrass05.wav</ShortName>
					<Path>SFX\FootstepGrass05_10F921B3.wem</Path>
				</File>
				<File Id="52008211" Language="SFX">
					<ShortName>ShipRopeCreak_0.wav</ShortName>
					<Path>SFX\ShipRopeCreak_0_10F921B3.wem</Path>
				</File>
				<File Id="52176852" Language="SFX">
					<ShortName>ImpactBluntFlesh-002.wav</ShortName>
					<Path>SFX\ImpactBluntFlesh-002_E1E65BF4.wem</Path>
				</File>
				<File Id="52579643" Language="SFX">
					<ShortName>FootSand-002.wav</ShortName>
					<Path>SFX\FootSand-002_10F921B3.wem</Path>
				</File>
				<File Id="53772691" Language="SFX">
					<ShortName>ImpactBluntFlesh-003.wav</ShortName>
					<Path>SFX\ImpactBluntFlesh-003_10F921B3.wem</Path>
				</File>
				<File Id="55573832" Language="SFX">
					<ShortName>FootstepGrass04.wav</ShortName>
					<Path>SFX\FootstepGrass04_10F921B3.wem</Path>
				</File>
				<File Id="57680030" Language="SFX">
					<ShortName>FootstepGrass02.wav</ShortName>
					<Path>SFX\FootstepGrass02_10F921B3.wem</Path>
				</File>
				<File Id="59156389" Language="SFX">
					<ShortName>ClubSwingHeavy03.wav</ShortName>
					<Path>SFX\ClubSwingHeavy03_6ECC79F2.wem</Path>
				</File>
				<File Id="60109241" Language="SFX">
					<ShortName>BoneBreaks-000.wav</ShortName>
					<Path>SFX\BoneBreaks-000_532346FA.wem</Path>
				</File>
				<File Id="61357554" Language="SFX">
					<ShortName>ImpactBluntFlesh-005.wav</ShortName>
					<Path>SFX\ImpactBluntFlesh-005_10F921B3.wem</Path>
				</File>
				<File Id="62354932" Language="SFX">
					<ShortName>FootRiverCoast-001.wav</ShortName>
					<Path>SFX\FootRiverCoast-001_10F921B3.wem</Path>
				</File>
				<File Id="63715012" Language="SFX">
					<ShortName>ShipSailFlap_0.wav</ShortName>
					<Path>SFX\ShipSailFlap_0_10F921B3.wem</Path>
				</File>
				<File Id="68803834" Language="SFX">
					<ShortName>FootRiverCoast-005.wav</ShortName>
					<Path>SFX\FootRiverCoast-005_10F921B3.wem</Path>
				</File>
				<File Id="77440121" Language="SFX">
					<ShortName>Vox_E_Death_00.wav</ShortName>
					<Path>SFX\Vox_E_Death_00_10F921B3.wem</Path>
				</File>
				<File Id="77828940" Language="SFX">
					<ShortName>ShipWoodCreakLow_2.wav</ShortName>
					<Path>SFX\ShipWoodCreakLow_2_10F921B3.wem</Path>
				</File>
				<File Id="80105195" Language="SFX">
					<ShortName>FootstepLeaves-009.wav</ShortName>
					<Path>SFX\FootstepLeaves-009_10F921B3.wem</Path>
				</File>
				<File Id="80608887" Language="SFX">
					<ShortName>ClubSwingHeavy01.wav</ShortName>
					<Path>SFX\ClubSwingHeavy01_6F326ED4.wem</Path>
				</File>
				<File Id="81044793" Language="SFX">
					<ShortName>FootstepMud04.wav</ShortName>
					<Path>SFX\FootstepMud04_10F921B3.wem</Path>
				</File>
				<File Id="82664685" Language="SFX">
					<ShortName>BuildImprovement-000.wav</ShortName>
					<Path>SFX\BuildImprovement-000_10F921B3.wem</Path>
				</File>
				<File Id="84804528" Language="SFX">
					<ShortName>ShipRunStop_1.wav</ShortName>
					<Path>SFX\ShipRunStop_1_10F921B3.wem</Path>
				</File>
				<File Id="84946747" Language="SFX">
					<ShortName>FootstepGrass01.wav</ShortName>
					<Path>SFX\FootstepGrass01_10F921B3.wem</Path>
				</File>
				<File Id="85007329" Language="SFX">
					<ShortName>ImpactBluntFlesh-006.wav</ShortName>
					<Path>SFX\ImpactBluntFlesh-006_10F921B3.wem</Path>
				</File>
				<File Id="86900743" Language="SFX">
					<ShortName>ClubSwingHeavy00.wav</ShortName>
					<Path>SFX\ClubSwingHeavy00_10F921B3.wem</Path>
				</File>
				<File Id="88740180" Language="SFX">
					<ShortName>ShipRunSplash_2.wav</ShortName>
					<Path>SFX\ShipRunSplash_2_10F921B3.wem</Path>
				</File>
				<File Id="88970538" Language="SFX">
					<ShortName>FootRiverCoast-004.wav</ShortName>
					<Path>SFX\FootRiverCoast-004_10F921B3.wem</Path>
				</File>
				<File Id="89353241" Language="SFX">
					<ShortName>CaravelRunStart_1.wav</ShortName>
					<Path>SFX\CaravelRunStart_1_10F921B3.wem</Path>
				</File>
				<File Id="89639444" Language="SFX">
					<ShortName>FoleyLeatherMetalsLightShort-003.wav</ShortName>
					<Path>SFX\FoleyLeatherMetalsLightShort-003_10F921B3.wem</Path>
				</File>
				<File Id="91573916" Language="SFX">
					<ShortName>BoneBreaks-003.wav</ShortName>
					<Path>SFX\BoneBreaks-003_8B249501.wem</Path>
				</File>
				<File Id="94442314" Language="SFX">
					<ShortName>FootstepMud01.wav</ShortName>
					<Path>SFX\FootstepMud01_10F921B3.wem</Path>
				</File>
				<File Id="97701314" Language="SFX">
					<ShortName>FootstepDirt03.wav</ShortName>
					<Path>SFX\FootstepDirt03_10F921B3.wem</Path>
				</File>
				<File Id="98544872" Language="SFX">
					<ShortName>FootSnow-001.wav</ShortName>
					<Path>SFX\FootSnow-001_10F921B3.wem</Path>
				</File>
				<File Id="99307177" Language="SFX">
					<ShortName>ShipRunSplash_3.wav</ShortName>
					<Path>SFX\ShipRunSplash_3_10F921B3.wem</Path>
				</File>
				<File Id="101513892" Language="SFX">
					<ShortName>FoleyLeatherMetalsLightShort-004.wav</ShortName>
					<Path>SFX\FoleyLeatherMetalsLightShort-004_10F921B3.wem</Path>
				</File>
				<File Id="107161087" Language="SFX">
					<ShortName>ImpactBluntFlesh-006.wav</ShortName>
					<Path>SFX\ImpactBluntFlesh-006_E1E65BF4.wem</Path>
				</File>
				<File Id="114512124" Language="SFX">
					<ShortName>Vox_E_Death_05.wav</ShortName>
					<Path>SFX\Vox_E_Death_05_10F921B3.wem</Path>
				</File>
				<File Id="117872342" Language="SFX">
					<ShortName>FootstepDirt01.wav</ShortName>
					<Path>SFX\FootstepDirt01_10F921B3.wem</Path>
				</File>
				<File Id="119813251" Language="SFX">
					<ShortName>CaravelRunLoop.wav</ShortName>
					<Path>SFX\CaravelRunLoop_70EA6DC1.wem</Path>
				</File>
				<File Id="124241496" Language="SFX">
					<ShortName>FootSand-000.wav</ShortName>
					<Path>SFX\FootSand-000_10F921B3.wem</Path>
				</File>
				<File Id="126507239" Language="SFX">
					<ShortName>FootstepGrass00.wav</ShortName>
					<Path>SFX\FootstepGrass00_10F921B3.wem</Path>
				</File>
				<File Id="130572846" Language="SFX">
					<ShortName>ShipSailFlap_5.wav</ShortName>
					<Path>SFX\ShipSailFlap_5_10F921B3.wem</Path>
				</File>
				<File Id="135619989" Language="SFX">
					<ShortName>FootstepDirt04.wav</ShortName>
					<Path>SFX\FootstepDirt04_10F921B3.wem</Path>
				</File>
				<File Id="136656065" Language="SFX">
					<ShortName>FoleyClothShort-003.wav</ShortName>
					<Path>SFX\FoleyClothShort-003_10F921B3.wem</Path>
				</File>
				<File Id="138962642" Language="SFX">
					<ShortName>BoneBreaks-004.wav</ShortName>
					<Path>SFX\BoneBreaks-004_81208CA3.wem</Path>
				</File>
				<File Id="140374253" Language="SFX">
					<ShortName>Vox_E_Death_03.wav</ShortName>
					<Path>SFX\Vox_E_Death_03_10F921B3.wem</Path>
				</File>
				<File Id="140526274" Language="SFX">
					<ShortName>Vox_E_Death_02.wav</ShortName>
					<Path>SFX\Vox_E_Death_02_10F921B3.wem</Path>
				</File>
				<File Id="142874496" Language="SFX">
					<ShortName>FoleyLeatherMetalsLightShort-007.wav</ShortName>
					<Path>SFX\FoleyLeatherMetalsLightShort-007_10F921B3.wem</Path>
				</File>
				<File Id="143161388" Language="SFX">
					<ShortName>FootstepDirt02.wav</ShortName>
					<Path>SFX\FootstepDirt02_10F921B3.wem</Path>
				</File>
				<File Id="148162661" Language="SFX">
					<ShortName>FoleyBagsAncient1.wav</ShortName>
					<Path>SFX\FoleyBagsAncient1_10F921B3.wem</Path>
				</File>
				<File Id="150065346" Language="SFX">
					<ShortName>Vox_E_Death_06.wav</ShortName>
					<Path>SFX\Vox_E_Death_06_10F921B3.wem</Path>
				</File>
				<File Id="150459554" Language="SFX">
					<ShortName>FootstepLeaves-004.wav</ShortName>
					<Path>SFX\FootstepLeaves-004_10F921B3.wem</Path>
				</File>
				<File Id="163533192" Language="SFX">
					<ShortName>FootstepLeaves-005.wav</ShortName>
					<Path>SFX\FootstepLeaves-005_10F921B3.wem</Path>
				</File>
				<File Id="168027614" Language="SFX">
					<ShortName>FoleyBagsAncient4.wav</ShortName>
					<Path>SFX\FoleyBagsAncient4_10F921B3.wem</Path>
				</File>
				<File Id="168331055" Language="SFX">
					<ShortName>FoleyLeatherMetalsLightShort-001.wav</ShortName>
					<Path>SFX\FoleyLeatherMetalsLightShort-001_10F921B3.wem</Path>
				</File>
				<File Id="176060008" Language="SFX">
					<ShortName>ImpactBluntFlesh-007.wav</ShortName>
					<Path>SFX\ImpactBluntFlesh-007_10F921B3.wem</Path>
				</File>
				<File Id="196921606" Language="SFX">
					<ShortName>ImpactBluntFlesh-003.wav</ShortName>
					<Path>SFX\ImpactBluntFlesh-003_E1E65BF4.wem</Path>
				</File>
				<File Id="208467243" Language="SFX">
					<ShortName>SwordSwoosh01.wav</ShortName>
					<Path>SFX\SwordSwoosh01_10F921B3.wem</Path>
				</File>
				<File Id="208623129" Language="SFX">
					<ShortName>FootSnow-000.wav</ShortName>
					<Path>SFX\FootSnow-000_10F921B3.wem</Path>
				</File>
				<File Id="218148112" Language="SFX">
					<ShortName>FootSand-003.wav</ShortName>
					<Path>SFX\FootSand-003_10F921B3.wem</Path>
				</File>
				<File Id="231499466" Language="SFX">
					<ShortName>BoneBreaks-000.wav</ShortName>
					<Path>SFX\BoneBreaks-000_311E3611.wem</Path>
				</File>
				<File Id="232957535" Language="SFX">
					<ShortName>FootSnow-005.wav</ShortName>
					<Path>SFX\FootSnow-005_10F921B3.wem</Path>
				</File>
				<File Id="236023140" Language="SFX">
					<ShortName>SwordSwoosh04.wav</ShortName>
					<Path>SFX\SwordSwoosh04_F9B3FB39.wem</Path>
				</File>
				<File Id="259106779" Language="SFX">
					<ShortName>FootSnow-002.wav</ShortName>
					<Path>SFX\FootSnow-002_10F921B3.wem</Path>
				</File>
				<File Id="260502492" Language="SFX">
					<ShortName>FoleyClothShort-005.wav</ShortName>
					<Path>SFX\FoleyClothShort-005_10F921B3.wem</Path>
				</File>
				<File Id="263557934" Language="SFX">
					<ShortName>ImpactBluntFlesh-001.wav</ShortName>
					<Path>SFX\ImpactBluntFlesh-001_10F921B3.wem</Path>
				</File>
				<File Id="280429713" Language="SFX">
					<ShortName>ShipSailFlap_9.wav</ShortName>
					<Path>SFX\ShipSailFlap_9_10F921B3.wem</Path>
				</File>
				<File Id="298859041" Language="SFX">
					<ShortName>FoleyLeatherMetalsLightShort-006.wav</ShortName>
					<Path>SFX\FoleyLeatherMetalsLightShort-006_10F921B3.wem</Path>
				</File>
				<File Id="335489461" Language="SFX">
					<ShortName>FoleyLeatherMetalsLightShort-000.wav</ShortName>
					<Path>SFX\FoleyLeatherMetalsLightShort-000_10F921B3.wem</Path>
				</File>
				<File Id="337600796" Language="SFX">
					<ShortName>ClubSwingHeavy02.wav</ShortName>
					<Path>SFX\ClubSwingHeavy02_587D869E.wem</Path>
				</File>
				<File Id="350312693" Language="SFX">
					<ShortName>ImpactBluntFlesh-000.wav</ShortName>
					<Path>SFX\ImpactBluntFlesh-000_E1E65BF4.wem</Path>
				</File>
				<File Id="360315961" Language="SFX">
					<ShortName>BoneBreaks-005.wav</ShortName>
					<Path>SFX\BoneBreaks-005_B7F1551A.wem</Path>
				</File>
				<File Id="361596621" Language="SFX">
					<ShortName>ClubSwingHeavy00.wav</ShortName>
					<Path>SFX\ClubSwingHeavy00_B4BE8B45.wem</Path>
				</File>
				<File Id="380425656" Language="SFX">
					<ShortName>ImpactBluntFlesh-005.wav</ShortName>
					<Path>SFX\ImpactBluntFlesh-005_E1E65BF4.wem</Path>
				</File>
				<File Id="386560024" Language="SFX">
					<ShortName>FoleyClothShort-004.wav</ShortName>
					<Path>SFX\FoleyClothShort-004_10F921B3.wem</Path>
				</File>
				<File Id="439005210" Language="SFX">
					<ShortName>FoleyClothShort-008.wav</ShortName>
					<Path>SFX\FoleyClothShort-008_10F921B3.wem</Path>
				</File>
				<File Id="440706936" Language="SFX">
					<ShortName>FoleyClothShort-002.wav</ShortName>
					<Path>SFX\FoleyClothShort-002_10F921B3.wem</Path>
				</File>
				<File Id="502366930" Language="SFX">
					<ShortName>Apostle_Attack_Strike_1.wav</ShortName>
					<Path>SFX\Apostle_Attack_Strike_1_E1E65BF4.wem</Path>
				</File>
				<File Id="520019763" Language="SFX">
					<ShortName>Leader_Phillip_SwordUnsheath-04.wav</ShortName>
					<Path>SFX\Leader_Phillip_SwordUnsheath-04_218BCA4E.wem</Path>
				</File>
				<File Id="524655305" Language="SFX">
					<ShortName>FoleyBagsAncient3.wav</ShortName>
					<Path>SFX\FoleyBagsAncient3_10F921B3.wem</Path>
				</File>
				<File Id="526301779" Language="SFX">
					<ShortName>FoleyLeatherMetalsLightShort-002.wav</ShortName>
					<Path>SFX\FoleyLeatherMetalsLightShort-002_10F921B3.wem</Path>
				</File>
				<File Id="551272722" Language="SFX">
					<ShortName>Apostle_Spread_Religion_InitialBurst.wav</ShortName>
					<Path>SFX\Apostle_Spread_Religion_InitialBurst_E1E65BF4.wem</Path>
				</File>
				<File Id="580062048" Language="SFX">
					<ShortName>BoneBreaks-006.wav</ShortName>
					<Path>SFX\BoneBreaks-006_ED12461E.wem</Path>
				</File>
				<File Id="608843785" Language="SFX">
					<ShortName>FoleyClothShort-007.wav</ShortName>
					<Path>SFX\FoleyClothShort-007_10F921B3.wem</Path>
				</File>
				<File Id="610919108" Language="SFX">
					<ShortName>SwordSwoosh04.wav</ShortName>
					<Path>SFX\SwordSwoosh04_10F921B3.wem</Path>
				</File>
				<File Id="625710359" Language="SFX">
					<ShortName>FoleyLeatherMetalsLightShort-009.wav</ShortName>
					<Path>SFX\FoleyLeatherMetalsLightShort-009_10F921B3.wem</Path>
				</File>
				<File Id="645162911" Language="SFX">
					<ShortName>BoneBreaks-003.wav</ShortName>
					<Path>SFX\BoneBreaks-003_1D4D6DD2.wem</Path>
				</File>
				<File Id="657161048" Language="SFX">
					<ShortName>SwordSwoosh03.wav</ShortName>
					<Path>SFX\SwordSwoosh03_10F921B3.wem</Path>
				</File>
				<File Id="675721536" Language="SFX">
					<ShortName>ClubSwingHeavy01.wav</ShortName>
					<Path>SFX\ClubSwingHeavy01_4E0AB5FC.wem</Path>
				</File>
				<File Id="677997766" Language="SFX">
					<ShortName>SwordSwoosh03.wav</ShortName>
					<Path>SFX\SwordSwoosh03_4602CD5E.wem</Path>
				</File>
				<File Id="687946855" Language="SFX">
					<ShortName>SwordSwoosh01.wav</ShortName>
					<Path>SFX\SwordSwoosh01_1562B4D8.wem</Path>
				</File>
				<File Id="724674789" Language="SFX">
					<ShortName>ImpactBluntFlesh-004.wav</ShortName>
					<Path>SFX\ImpactBluntFlesh-004_E1E65BF4.wem</Path>
				</File>
				<File Id="731730116" Language="SFX">
					<ShortName>DeathKnell-01.wav</ShortName>
					<Path>SFX\DeathKnell-01_E1E65BF4.wem</Path>
				</File>
				<File Id="733222401" Language="SFX">
					<ShortName>Apostle_Attack_Strike_0.wav</ShortName>
					<Path>SFX\Apostle_Attack_Strike_0_E1E65BF4.wem</Path>
				</File>
				<File Id="747669790" Language="SFX">
					<ShortName>ImpactBluntFlesh-001.wav</ShortName>
					<Path>SFX\ImpactBluntFlesh-001_E1E65BF4.wem</Path>
				</File>
				<File Id="759967522" Language="SFX">
					<ShortName>FoleyLeatherMetalsLightShort-008.wav</ShortName>
					<Path>SFX\FoleyLeatherMetalsLightShort-008_10F921B3.wem</Path>
				</File>
				<File Id="774569519" Language="SFX">
					<ShortName>FoleyLeatherMetalsLightShort-005.wav</ShortName>
					<Path>SFX\FoleyLeatherMetalsLightShort-005_10F921B3.wem</Path>
				</File>
				<File Id="845075357" Language="SFX">
					<ShortName>FoleyBagsAncient2.wav</ShortName>
					<Path>SFX\FoleyBagsAncient2_10F921B3.wem</Path>
				</File>
				<File Id="855594199" Language="SFX">
					<ShortName>BoneBreaks-005.wav</ShortName>
					<Path>SFX\BoneBreaks-005_0DD2AE2D.wem</Path>
				</File>
				<File Id="867416558" Language="SFX">
					<ShortName>FoleyClothShort-000.wav</ShortName>
					<Path>SFX\FoleyClothShort-000_10F921B3.wem</Path>
				</File>
				<File Id="872245341" Language="SFX">
					<ShortName>Apostle_Spread_Religion.wav</ShortName>
					<Path>SFX\Apostle_Spread_Religion_E1E65BF4.wem</Path>
				</File>
				<File Id="881830445" Language="SFX">
					<ShortName>FoleyClothShort-001.wav</ShortName>
					<Path>SFX\FoleyClothShort-001_10F921B3.wem</Path>
				</File>
				<File Id="956262293" Language="SFX">
					<ShortName>BoneBreaks-006.wav</ShortName>
					<Path>SFX\BoneBreaks-006_4BF7B0C5.wem</Path>
				</File>
				<File Id="982445217" Language="SFX">
					<ShortName>Apostle_Attack_Strike_2.wav</ShortName>
					<Path>SFX\Apostle_Attack_Strike_2_E1E65BF4.wem</Path>
				</File>
				<File Id="1026662326" Language="SFX">
					<ShortName>BuildImprovement-001.wav</ShortName>
					<Path>SFX\BuildImprovement-001_10F921B3.wem</Path>
				</File>
				<File Id="1058395471" Language="SFX">
					<ShortName>ImpactBluntFlesh-007.wav</ShortName>
					<Path>SFX\ImpactBluntFlesh-007_E1E65BF4.wem</Path>
				</File>
			</IncludedMemoryFiles>
		</SoundBank>
	</SoundBanks>
</SoundBanksInfo>
