<?xml version="1.0" encoding="utf-8"?>
<Context>

  <Container Style="FullScreenVignetteConsumer"/>

  <Grid ID="DropShadow" Size="595,768" Anchor="C,C" Offset="0,0" Style="DropShadow2" Color="255,255,255,200">
    <Grid ID="Window" Size="parent-5,parent+8" Anchor="C,C" Offset="0,0" SizePadding="0,20" Style="EventPopupFrame">

      <Grid Style="EventPopupTitleBar" Size="parent-32,65" Offset="0,17" Anchor="C,T">
        <Label ID="EventTitle" Style="EventPopupTitle" Offset="0,2" Align="Center" WrapWidth="420" String="LOC_DISCOVERED_SOCIETY" Anchor="C,C"/>
      </Grid>
      
      <Container ID="DescriptionContainer" Size="parent-32,60" Offset="0,80" Anchor="C,T">
        <Label ID="EventDescription" Style="EventPopupDescription" Align="Center" WrapWidth="parent-40" Anchor="C,C"/>
        <Line Start="1,0" End="parent-2,0" Width="2" Color="35,66,92,150" Anchor="C,B"/>
      </Container>
      
      <Image ID="SocietyImage" Size="296,360" Texture="SecretSocieties_EventsFG_Discover" Anchor="C,T" Offset="0,140"/>

      <Grid Style="EventPopupEffectsDeco" Anchor="C,B" Offset="0,115" Size="parent-50,160" AutoSizePadding="0,10">
        <ScrollPanel Size="parent-25,parent-10" Anchor="C,C" Vertical="1" AutoScrollBar="1">  
          <ScrollBar Size="11,100" Anchor="R,C"  Offset="0,0" Style="ScrollVerticalBar" />  
          <Label ID="SocietyDescription" Style="EventPopupEffects" Size="parent,auto" Align="Center" WrapWidth="parent-50" Anchor="C,C"/>
        </ScrollPanel>
      </Grid>

      <Stack ID="ButtonStack" Anchor="C,B" Offset="0,26" StackPadding="4" StackGrowth="Down">
        <GridButton ID="OpenGovernorsButton" Style="MainButton" Size="270,40" Anchor="C,T" Offset="0,0" String="LOC_GO_TO_GOVERNORS"/>
        <GridButton ID="ContinueButton" Style="MainButton" Size="270,40" Anchor="C,T" Offset="0,0" String="LOC_CONTINUE"/>
      </Stack>
    </Grid>
  </Grid>
  
</Context>