<?xml version="1.0" encoding="utf-8"?>
<SoundBanksInfo Platform="Windows" BasePlatform="Windows" SchemaVersion="10" SoundbankVersion="113">
	<RootPaths>
		<ProjectRoot>C:\projects\civ6\Civ6\Wwise\Civ6 Project\</ProjectRoot>
		<SourceFilesRoot>C:\projects\civ6\Civ6\Wwise\Civ6 Project\.cache\Windows\</SourceFilesRoot>
		<SoundBanksRoot>C:\projects\civ6\Civ6\Wwise\Civ6 Project\GeneratedSoundBanks\Windows\</SoundBanksRoot>
		<ExternalSourcesInputFile></ExternalSourcesInputFile>
		<ExternalSourcesOutputRoot>C:\projects\civ6\Civ6\Wwise\Civ6 Project\GeneratedSoundBanks\Windows</ExternalSourcesOutputRoot>
	</RootPaths>
	<SoundBanks>
		<SoundBank Id="467466383" GUID="{0A7E1ADC-C7D8-4E3F-9581-355888170529}" Language="SFX">
			<ShortName>XP3_DLC6_Unit_Bank_2D</ShortName>
			<Path>XP3_DLC6_Unit_Bank_2D.bnk</Path>
			<IncludedEvents>
				<Event Id="3749595601" Name="Zombie_ReleaseControl_2D" GUID="{18365C9D-B455-4704-94A6-11C9CD8AA3B9}"/>
			</IncludedEvents>
			<IncludedMemoryFiles>
				<File Id="744335863" Language="SFX">
					<ShortName>Zombies_Release_Control_02.wav</ShortName>
					<Path>SFX\Zombies_Release_Control_02_90FD7A8B.wem</Path>
				</File>
			</IncludedMemoryFiles>
		</SoundBank>
	</SoundBanks>
</SoundBanksInfo>
